LICENSE
MANIFEST.in
README.md
setup.py
downloaders/__init__.py
downloaders/__version__.py
downloaders/py.typed
downloaders/utils.py
downloaders.egg-info/PKG-INFO
downloaders.egg-info/SOURCES.txt
downloaders.egg-info/dependency_links.txt
downloaders.egg-info/requires.txt
downloaders.egg-info/top_level.txt
downloaders/downloaders/__init__.py
downloaders/downloaders/base_downloader.py
downloaders/extractors/__init__.py
downloaders/extractors/auto_extractor.py
downloaders/extractors/base_extractor.py
downloaders/extractors/bz2_extractor.py
downloaders/extractors/gzip_extractor.py
downloaders/extractors/tar_extractor.py
downloaders/extractors/targz_extractor.py
downloaders/extractors/utils.py
downloaders/extractors/xz_extractor.py
downloaders/extractors/zip_extraction.py