Metadata-Version: 2.1
Name: downloaders
Version: 1.0.22
Summary: Python package to handle download of multiple types of files.
Home-page: https://github.com/LucaCappelletti94/downloaders
Author: LucaCappelletti94
Author-email: cappelletti.luca94@gmail.com
License: MIT
Platform: UNKNOWN
Classifier: Development Status :: 5 - Production/Stable
Classifier: License :: OSI Approved :: MIT License
Classifier: Programming Language :: Python :: 3
Requires-Python: >=3.8
Provides-Extra: test
License-File: LICENSE
